mailme/__init__.py
mailme/main.py
mailme/controllers/__init__.py
mailme/controllers/api/__init__.py
mailme/controllers/api/base.py
mailme/controllers/web/__init__.py
mailme/controllers/web/admin.py
mailme/controllers/web/base.py
mailme/models/__init__.py
mailme/models/base.py
mailme/models/message.py
mailme/templates/admin/applier.html.tpl
mailme/templates/email/base.html.tpl
mailme/templates/email/base.inline.html.tpl
mailme/templates/email/layout.html.tpl
mailme/templates/email/layout.inline.html.tpl
mailme/templates/email/macros.html.tpl
mailme/templates/email/test.html.tpl
mailme/templates/styles/base.html.tpl
mailme/templates/styles/dark.html.tpl
mailme/templates/styles/extra.html.tpl
mailme_py-0.1.5.dist-info/METADATA
mailme_py-0.1.5.dist-info/WHEEL
mailme_py-0.1.5.dist-info/top_level.txt
mailme_py-0.1.5.dist-info/RECORD
